exfor_tools/__init__.py
exfor_tools/__version__.py
exfor_tools/curate.py
exfor_tools/db.py
exfor_tools/distribution.py
exfor_tools/exfor_entry.py
exfor_tools/parsing.py
exfor_tools/reaction.py
exfor_tools-0.3.1.dist-info/licenses/LICENSE
exfor_tools-0.3.1.dist-info/METADATA
exfor_tools-0.3.1.dist-info/WHEEL
exfor_tools-0.3.1.dist-info/top_level.txt
exfor_tools-0.3.1.dist-info/RECORD
