Metadata-Version: 2.4
Name: exfor_tools
Version: 0.3.1
Summary: A lightweight interface to grab and organize differential cross sections from EXFOR, using the x4i3 library.
Author: Kyle Beyer
License: MIT License
Classifier: Programming Language :: Python :: 3
Classifier: License :: OSI Approved :: GNU General Public License v3 (GPLv3)
Classifier: Operating System :: OS Independent
Requires-Python: >=3.10
License-File: LICENSE
Requires-Dist: numpy>=1.21.5
Requires-Dist: x4i3>=1.2.0
Requires-Dist: periodictable>1.0
Dynamic: license-file
